{
    "id": "money",
    "translations": {
        "en": {
            "text": "money",
            "exampleSentence": "I need to save some money.",
            "pronunciations": {
                "tr": "ma·ni",
                "en": "mun·ee",
                "es": "ma·ni",
                "id": "ma·ni",
                "fr": "ma·ni",
                "it": "ma·ni",
                "pt": "ma·ni",
                "zh": "马·尼",
                "ru": "ма·ни",
                "ja": "マ·ニー",
                "hi": "म·नी",
                "fil": "ma·ni",
                "th": "มั·นี",
                "ko": "머·니",
                "nl": "mun·nie",
                "sv": "ma·ni",
                "pl": "ma·ni",
                "el": "μά·νι",
                "de": "ma·ni"
            }
        },
        "tr": {
            "text": "para",
            "exampleSentence": "Biraz para biriktirmem gerek.",
            "pronunciations": {
                "tr": "pa·ra",
                "en": "pah·rah",
                "es": "pa·ra",
                "id": "pa·ra",
                "fr": "pa·ra",
                "it": "pa·ra",
                "pt": "pa·ra",
                "zh": "帕·拉",
                "ru": "па·ра",
                "ja": "パ·ラ",
                "hi": "पा·रा",
                "fil": "pa·ra",
                "th": "พา·รา",
                "ko": "파·라",
                "nl": "pa·ra",
                "sv": "pa·ra",
                "pl": "pa·ra",
                "el": "πά·ρα",
                "de": "pa·ra"
            }
        },
        "es": {
            "text": "dinero",
            "exampleSentence": "Necesito ahorrar dinero.",
            "pronunciations": {
                "tr": "di·ne·ro",
                "en": "dee·neh·ro",
                "es": "di·ne·ro",
                "id": "di·ne·ro",
                "fr": "di·ne·ro",
                "it": "di·ne·ro",
                "pt": "di·ne·ro",
                "zh": "迪·内·罗",
                "ru": "ди·не·ро",
                "ja": "ディ·ネ·ロ",
                "hi": "दी·ने·रो",
                "fil": "di·ne·ro",
                "th": "ดี·เน·โร",
                "ko": "디·네·로",
                "nl": "di·ne·ro",
                "sv": "di·ne·ro",
                "pl": "di·ne·ro",
                "el": "ντι·νέ·ρο",
                "de": "di·ne·ro"
            }
        },
        "id": {
            "text": "uang",
            "exampleSentence": "Saya perlu menabung uang.",
            "pronunciations": {
                "tr": "u·ang",
                "en": "oo·ahng",
                "es": "u·ang",
                "id": "u·ang",
                "fr": "u·ang",
                "it": "u·ang",
                "pt": "u·ang",
                "zh": "乌·昂",
                "ru": "у·анг",
                "ja": "ウ·アン",
                "hi": "उ·आंग",
                "fil": "u·ang",
                "th": "อู·อัง",
                "ko": "우·앙",
                "nl": "oe·ang",
                "sv": "u·ang",
                "pl": "u·ang",
                "el": "ου·άνγκ",
                "de": "u·ang"
            }
        },
        "fr": {
            "text": "argent",
            "exampleSentence": "J'ai besoin d'économiser de l'argent.",
            "pronunciations": {
                "tr": "ar·jan",
                "en": "ar·zhahn",
                "es": "ar·yan",
                "id": "ar·jan",
                "fr": "ar·gent",
                "it": "ar·jan",
                "pt": "ar·jan",
                "zh": "阿尔·让",
                "ru": "ар·жан",
                "ja": "アル·ジャン",
                "hi": "आर·जां",
                "fil": "ar·jan",
                "th": "อาร์·ฌ็อง",
                "ko": "아르·장",
                "nl": "ar·zjan",
                "sv": "ar·sjang",
                "pl": "ar·żą",
                "el": "αρ·ζάν",
                "de": "ar·schang"
            }
        },
        "it": {
            "text": "soldi",
            "exampleSentence": "Ho bisogno di risparmiare soldi.",
            "pronunciations": {
                "tr": "sol·di",
                "en": "sohl·dee",
                "es": "sol·di",
                "id": "sol·di",
                "fr": "sol·di",
                "it": "sol·di",
                "pt": "sol·di",
                "zh": "索尔·迪",
                "ru": "соль·ди",
                "ja": "ソル·ディ",
                "hi": "सोल्·दी",
                "fil": "sol·di",
                "th": "โซล·ดี",
                "ko": "솔·디",
                "nl": "sol·di",
                "sv": "sol·di",
                "pl": "sol·di",
                "el": "σόλ·ντι",
                "de": "sol·di"
            }
        },
        "pt": {
            "text": "dinheiro",
            "exampleSentence": "Preciso economizar dinheiro.",
            "pronunciations": {
                "tr": "din·hey·ro",
                "en": "deen·yay·roo",
                "es": "di·ney·ro",
                "id": "din·he·ro",
                "fr": "di·nye·ro",
                "it": "di·nye·ro",
                "pt": "di·nhei·ro",
                "zh": "丁·海·罗",
                "ru": "динь·ей·ру",
                "ja": "ジ·ネイ·ロ",
                "hi": "दीन्·हे·रो",
                "fil": "din·he·ro",
                "th": "ดิน·เฮ·โร",
                "ko": "딘·헤이·로",
                "nl": "din·hei·ro",
                "sv": "din·hej·ro",
                "pl": "din·hej·ro",
                "el": "ντι·νέι·ρο",
                "de": "din·hei·ro"
            }
        },
        "zh": {
            "text": "钱",
            "romanized": "qián",
            "exampleSentence": "我需要存钱。",
            "romanizedExample": "Wǒ xūyào cún qián.",
            "pronunciations": {
                "tr": "çi·en",
                "en": "chee·en",
                "es": "chi·en",
                "id": "qi·an",
                "fr": "tchi·en",
                "it": "ci·en",
                "pt": "qi·an",
                "zh": "钱",
                "ru": "ци·янь",
                "ja": "チェン",
                "hi": "ची·एन",
                "fil": "chi·en",
                "th": "เชียน",
                "ko": "치·엔",
                "nl": "tji·en",
                "sv": "tji·en",
                "pl": "ci·en",
                "el": "τσι·έν",
                "de": "tsi·en"
            }
        },
        "ru": {
            "text": "деньги",
            "romanized": "dengi",
            "exampleSentence": "Мне нужно копить деньги.",
            "romanizedExample": "Mne nuzhno kopit dengi.",
            "pronunciations": {
                "tr": "den·gi",
                "en": "dyen·gee",
                "es": "den·gui",
                "id": "den·gi",
                "fr": "dien·gui",
                "it": "den·ghi",
                "pt": "den·gui",
                "zh": "杰·尼基",
                "ru": "день·ги",
                "ja": "ジェン·ギ",
                "hi": "देन्·गी",
                "fil": "den·gi",
                "th": "เดน·กี",
                "ko": "덴·기",
                "nl": "djen·gi",
                "sv": "den·gi",
                "pl": "dien·gi",
                "el": "ντέν·γκι",
                "de": "den·gi"
            }
        },
        "ja": {
            "text": "お金",
            "romanized": "okane",
            "exampleSentence": "お金を貯める必要があります。",
            "romanizedExample": "Okane wo tameru hitsuyou ga arimasu.",
            "pronunciations": {
                "tr": "o·ka·ne",
                "en": "oh·kah·neh",
                "es": "o·ka·ne",
                "id": "o·ka·ne",
                "fr": "o·ka·ne",
                "it": "o·ka·ne",
                "pt": "o·ka·ne",
                "zh": "奥·卡·内",
                "ru": "о·ка·нэ",
                "ja": "お·か·ね",
                "hi": "ओ·का·ने",
                "fil": "o·ka·ne",
                "th": "โอ·คา·เนะ",
                "ko": "오·카·네",
                "nl": "o·ka·ne",
                "sv": "o·ka·ne",
                "pl": "o·ka·ne",
                "el": "ο·κά·νε",
                "de": "o·ka·ne"
            }
        },
        "hi": {
            "text": "पैसा",
            "romanized": "paisa",
            "exampleSentence": "मुझे पैसे बचाने की जरूरत है।",
            "romanizedExample": "Mujhe paise bachane ki zarurat hai.",
            "pronunciations": {
                "tr": "pay·sa",
                "en": "pai·sah",
                "es": "pai·sa",
                "id": "pai·sa",
                "fr": "paï·sa",
                "it": "pai·sa",
                "pt": "pai·sa",
                "zh": "派·萨",
                "ru": "пай·са",
                "ja": "パイ·サ",
                "hi": "पै·सा",
                "fil": "pai·sa",
                "th": "ไพ·ซา",
                "ko": "파이·사",
                "nl": "pai·sa",
                "sv": "pai·sa",
                "pl": "paj·sa",
                "el": "πάι·σα",
                "de": "pai·sa"
            }
        },
        "fil": {
            "text": "pera",
            "exampleSentence": "Kailangan kong mag-ipon ng pera.",
            "pronunciations": {
                "tr": "pe·ra",
                "en": "peh·rah",
                "es": "pe·ra",
                "id": "pe·ra",
                "fr": "pe·ra",
                "it": "pe·ra",
                "pt": "pe·ra",
                "zh": "佩·拉",
                "ru": "пе·ра",
                "ja": "ペ·ラ",
                "hi": "पे·रा",
                "fil": "pe·ra",
                "th": "เป·รา",
                "ko": "페·라",
                "nl": "pe·ra",
                "sv": "pe·ra",
                "pl": "pe·ra",
                "el": "πέ·ρα",
                "de": "pe·ra"
            }
        },
        "th": {
            "text": "เงิน",
            "romanized": "ngern",
            "exampleSentence": "ฉันต้องการเก็บเงิน",
            "romanizedExample": "Chan tongkarn keb ngern.",
            "pronunciations": {
                "tr": "nğern",
                "en": "ngern",
                "es": "ngern",
                "id": "ngern",
                "fr": "ngern",
                "it": "ngern",
                "pt": "ngern",
                "zh": "恩格恩",
                "ru": "нгерн",
                "ja": "ゲーン",
                "hi": "नगर्न",
                "fil": "ngern",
                "th": "เงิน",
                "ko": "응언",
                "nl": "ngern",
                "sv": "ngern",
                "pl": "ngern",
                "el": "νγκερν",
                "de": "ngern"
            }
        },
        "ko": {
            "text": "돈",
            "romanized": "don",
            "exampleSentence": "돈을 저축해야 합니다.",
            "romanizedExample": "Don-eul jeochukaeya hamnida.",
            "pronunciations": {
                "tr": "don",
                "en": "dohn",
                "es": "don",
                "id": "don",
                "fr": "don",
                "it": "don",
                "pt": "don",
                "zh": "敦",
                "ru": "дон",
                "ja": "ドン",
                "hi": "दोन",
                "fil": "don",
                "th": "ดน",
                "ko": "돈",
                "nl": "don",
                "sv": "don",
                "pl": "don",
                "el": "ντον",
                "de": "don"
            }
        },
        "nl": {
            "text": "geld",
            "exampleSentence": "Ik moet geld sparen.",
            "pronunciations": {
                "tr": "helt",
                "en": "khelt",
                "es": "jeld",
                "id": "held",
                "fr": "gueld",
                "it": "gheld",
                "pt": "gueld",
                "zh": "赫尔德",
                "ru": "хелд",
                "ja": "ヘルト",
                "hi": "हेल्ड",
                "fil": "held",
                "th": "เฮลด์",
                "ko": "헬트",
                "nl": "geld",
                "sv": "held",
                "pl": "cheld",
                "el": "χελντ",
                "de": "geld"
            }
        },
        "sv": {
            "text": "pengar",
            "exampleSentence": "Jag behöver spara pengar.",
            "pronunciations": {
                "tr": "peng·ar",
                "en": "peng·ar",
                "es": "peng·ar",
                "id": "peng·ar",
                "fr": "peng·ar",
                "it": "peng·ar",
                "pt": "peng·ar",
                "zh": "彭·阿尔",
                "ru": "пенг·ар",
                "ja": "ペン·アル",
                "hi": "पेंग·अर",
                "fil": "peng·ar",
                "th": "เพง·อาร์",
                "ko": "펭·아르",
                "nl": "peng·ar",
                "sv": "peng·ar",
                "pl": "peng·ar",
                "el": "πενγκ·αρ",
                "de": "peng·ar"
            }
        },
        "pl": {
            "text": "pieniądze",
            "exampleSentence": "Muszę oszczędzać pieniądze.",
            "pronunciations": {
                "tr": "pye·nyon·dze",
                "en": "pyen·yon·dzeh",
                "es": "pie·nion·dze",
                "id": "pie·nion·dze",
                "fr": "pié·nion·dzé",
                "it": "pie·nion·dze",
                "pt": "pie·nion·dze",
                "zh": "皮耶·尼翁·泽",
                "ru": "пье·нён·дзе",
                "ja": "ピェ·ニョン·ゼ",
                "hi": "प्येन्·योन्·ज़े",
                "fil": "pye·nyon·dze",
                "th": "เปียน·ยอน·เซ",
                "ko": "피에·니온·제",
                "nl": "pje·njon·dze",
                "sv": "pje·njon·dze",
                "pl": "pie·nią·dze",
                "el": "πιε·νιόν·τζε",
                "de": "pje·njon·dse"
            }
        },
        "el": {
            "text": "χρήματα",
            "romanized": "chrímata",
            "exampleSentence": "Πρέπει να εξοικονομήσω χρήματα.",
            "romanizedExample": "Prépi na exoikonomíso chrímata.",
            "pronunciations": {
                "tr": "hri·ma·ta",
                "en": "khree·mah·tah",
                "es": "jri·ma·ta",
                "id": "hri·ma·ta",
                "fr": "khri·ma·ta",
                "it": "chri·ma·ta",
                "pt": "hri·ma·ta",
                "zh": "赫里·马·塔",
                "ru": "хри·ма·та",
                "ja": "フリ·マ·タ",
                "hi": "ख्री·मा·ता",
                "fil": "hri·ma·ta",
                "th": "คริ·มา·ทา",
                "ko": "흐리·마·타",
                "nl": "chri·ma·ta",
                "sv": "chri·ma·ta",
                "pl": "chri·ma·ta",
                "el": "χρή·μα·τα",
                "de": "chri·ma·ta"
            }
        },
        "de": {
            "text": "geld",
            "exampleSentence": "Ich muss Geld sparen.",
            "pronunciations": {
                "tr": "gelt",
                "en": "gelt",
                "es": "gueld",
                "id": "geld",
                "fr": "gueld",
                "it": "gheld",
                "pt": "gueld",
                "zh": "格尔德",
                "ru": "гельд",
                "ja": "ゲルト",
                "hi": "गेल्ड",
                "fil": "geld",
                "th": "เกลด์",
                "ko": "겔트",
                "nl": "geld",
                "sv": "geld",
                "pl": "geld",
                "el": "γκελντ",
                "de": "geld"
            }
        }
    }
}
