{
    "id": "sleepy",
    "translations": {
        "en": {
            "text": "sleepy",
            "exampleSentence": "You look sleepy, go rest.",
            "pronunciations": {
                "tr": "sli·pi",
                "en": "slee·py",
                "es": "sli·pi",
                "id": "sli·pi",
                "fr": "sli·pi",
                "it": "sli·pi",
                "pt": "sli·pi",
                "zh": "斯利·皮",
                "ru": "сли·пи",
                "ja": "スリー·ピー",
                "hi": "स्ली·पी",
                "fil": "sli·pi",
                "th": "สลี·พี",
                "ko": "슬리·피",
                "nl": "sli·pi",
                "sv": "sli·pi",
                "pl": "sli·pi",
                "el": "σλί·πι",
                "de": "sli·pi"
            }
        },
        "tr": {
            "text": "uykulu",
            "exampleSentence": "Uykulu görünüyorsun, git dinlen.",
            "pronunciations": {
                "tr": "uy·ku·lu",
                "en": "uy·ku·lu",
                "es": "ui·ku·lu",
                "id": "uy·ku·lu",
                "fr": "ouy·kou·lou",
                "it": "uy·ku·lu",
                "pt": "uy·ku·lu",
                "zh": "乌库·卢",
                "ru": "уй·ку·лу",
                "ja": "ウイ·ク·ル",
                "hi": "उय्·कु·लु",
                "fil": "uy·ku·lu",
                "th": "อุย·คู·ลู",
                "ko": "우이·쿠·루",
                "nl": "oej·koe·loe",
                "sv": "uj·ku·lu",
                "pl": "uj·ku·lu",
                "el": "ούι·κου·λου",
                "de": "uj·ku·lu"
            }
        },
        "es": {
            "text": "soñoliento",
            "exampleSentence": "Te ves soñoliento, ve a descansar.",
            "pronunciations": {
                "tr": "son·yo·li·en·to",
                "en": "son·yo·lee·en·to",
                "es": "so·ño·lien·to",
                "id": "so·nyo·li·en·to",
                "fr": "so·gno·li·en·to",
                "it": "so·nyo·li·en·to",
                "pt": "so·nyo·li·en·to",
                "zh": "索尼奥连托",
                "ru": "со·ньо·ли·ен·то",
                "ja": "ソ·ニョ·リ·エン·ト",
                "hi": "सो·न्यो·ली·एन·तो",
                "fil": "so·nyo·li·en·to",
                "th": "โซ·โญ·ลี·เอน·โต",
                "ko": "소·뇨·리·엔·토",
                "nl": "so·njo·li·en·to",
                "sv": "so·njo·li·en·to",
                "pl": "so·nio·li·en·to",
                "el": "σο·νιο·λι·έν·το",
                "de": "so·njo·li·en·to"
            }
        },
        "id": {
            "text": "mengantuk",
            "exampleSentence": "Kamu terlihat mengantuk, pergilah beristirahat.",
            "pronunciations": {
                "tr": "men·gan·tuk",
                "en": "meng·ahn·took",
                "es": "men·gan·tuk",
                "id": "me·ngan·tuk",
                "fr": "men·gan·touk",
                "it": "men·gan·tuk",
                "pt": "men·gan·tuk",
                "zh": "门甘图克",
                "ru": "мен·ган·тук",
                "ja": "メン·ガン·トゥク",
                "hi": "मेंग·अन्·तुक",
                "fil": "meng·an·tuk",
                "th": "เมง·กัน·ตุก",
                "ko": "멩·간·투크",
                "nl": "meng·an·toek",
                "sv": "meng·an·tuk",
                "pl": "meng·an·tuk",
                "el": "μενγκ·αν·τουκ",
                "de": "meng·an·tuk"
            }
        },
        "fr": {
            "text": "somnolent",
            "exampleSentence": "Tu as l'air somnolent, va te reposer.",
            "pronunciations": {
                "tr": "som·no·lan",
                "en": "som·no·lahn",
                "es": "som·no·lan",
                "id": "som·no·lan",
                "fr": "som·no·lent",
                "it": "som·no·lan",
                "pt": "som·no·lan",
                "zh": "索姆诺朗",
                "ru": "сом·но·лан",
                "ja": "ソム·ノ·ラン",
                "hi": "सोम्·नो·लां",
                "fil": "som·no·lan",
                "th": "ซม·โน·ลอง",
                "ko": "솜·노·랑",
                "nl": "som·no·lan",
                "sv": "som·no·lan",
                "pl": "som·no·ląt",
                "el": "σομ·νο·λάν",
                "de": "som·no·lan"
            }
        },
        "it": {
            "text": "assonnato",
            "exampleSentence": "Sembri assonnato, vai a riposarti.",
            "pronunciations": {
                "tr": "as·son·na·to",
                "en": "ah·son·nah·toh",
                "es": "a·so·na·to",
                "id": "as·son·na·to",
                "fr": "as·son·na·to",
                "it": "as·son·na·to",
                "pt": "as·son·na·to",
                "zh": "阿索纳托",
                "ru": "ас·сон·на·то",
                "ja": "アッ·ソン·ナ·ト",
                "hi": "अस्·सोन्·ना·तो",
                "fil": "as·son·na·to",
                "th": "อัส·ซอน·นา·โต",
                "ko": "아스·손·나·토",
                "nl": "as·son·na·to",
                "sv": "as·son·na·to",
                "pl": "as·son·na·to",
                "el": "ασ·σον·νά·το",
                "de": "as·son·na·to"
            }
        },
        "pt": {
            "text": "sonolento",
            "exampleSentence": "Você parece sonolento, vá descansar.",
            "pronunciations": {
                "tr": "so·no·len·to",
                "en": "so·no·len·to",
                "es": "so·no·len·to",
                "id": "so·no·len·to",
                "fr": "so·no·len·to",
                "it": "so·no·len·to",
                "pt": "so·no·len·to",
                "zh": "索诺伦托",
                "ru": "со·но·лен·то",
                "ja": "ソ·ノ·レン·ト",
                "hi": "सो·नो·लेन्·तो",
                "fil": "so·no·len·to",
                "th": "โซ·โน·เลน·โต",
                "ko": "소·노·렌·토",
                "nl": "so·no·len·to",
                "sv": "so·no·len·to",
                "pl": "so·no·len·to",
                "el": "σο·νο·λέν·το",
                "de": "so·no·len·to"
            }
        },
        "zh": {
            "text": "困倦",
            "romanized": "kùn juàn",
            "exampleSentence": "你看起来很困倦，去休息吧。",
            "romanizedExample": "Nǐ kàn qǐlái hěn kùn juàn, qù xiūxi ba.",
            "pronunciations": {
                "tr": "kun·cu·an",
                "en": "koon·jwan",
                "es": "kun·juan",
                "id": "kun·juan",
                "fr": "koun·jouan",
                "it": "kun·juan",
                "pt": "kun·juan",
                "zh": "困·倦",
                "ru": "кунь·цзюань",
                "ja": "クン·ジュアン",
                "hi": "कुन·ज्वान",
                "fil": "kun·juan",
                "th": "คุน·จวน",
                "ko": "쿤·쥐안",
                "nl": "koen·zjwan",
                "sv": "kun·juan",
                "pl": "kun·dzjuan",
                "el": "κουν·τζουάν",
                "de": "kun·juan"
            }
        },
        "ru": {
            "text": "сонный",
            "romanized": "sonnyy",
            "exampleSentence": "Ты выглядишь сонным, иди отдохни.",
            "romanizedExample": "Ty vyglyadish sonnym, idi otdokhni.",
            "pronunciations": {
                "tr": "son·nıy",
                "en": "son·ny",
                "es": "son·ni",
                "id": "son·ny",
                "fr": "son·ny",
                "it": "son·ny",
                "pt": "son·ny",
                "zh": "索尼",
                "ru": "сон·ный",
                "ja": "ソン·ヌイ",
                "hi": "सोन्·नी",
                "fil": "son·ny",
                "th": "ซอน·นี",
                "ko": "손·니",
                "nl": "son·ny",
                "sv": "son·ny",
                "pl": "son·ny",
                "el": "σόν·νι",
                "de": "son·ny"
            }
        },
        "ja": {
            "text": "眠い",
            "romanized": "nemui",
            "exampleSentence": "眠そうだね、休んでください。",
            "romanizedExample": "Nemui sou da ne, yasunde kudasai.",
            "pronunciations": {
                "tr": "ne·mu·i",
                "en": "neh·moo·ee",
                "es": "ne·mu·i",
                "id": "ne·mu·i",
                "fr": "ne·mou·i",
                "it": "ne·mu·i",
                "pt": "ne·mu·i",
                "zh": "内姆伊",
                "ru": "нэ·му·и",
                "ja": "ね·む·い",
                "hi": "ने·मु·ई",
                "fil": "ne·mu·i",
                "th": "เนะ·มุ·อิ",
                "ko": "네·무·이",
                "nl": "ne·moe·i",
                "sv": "ne·mu·i",
                "pl": "ne·mu·i",
                "el": "νε·μου·ι",
                "de": "ne·mu·i"
            }
        },
        "hi": {
            "text": "नींद भरी",
            "romanized": "neend bhari",
            "exampleSentence": "तुम नींद भरी लग रहे हो, जाकर आराम करो।",
            "romanizedExample": "Tum neend bhari lag rahe ho, jaakar aaram karo.",
            "pronunciations": {
                "tr": "nind·ba·ri",
                "en": "neend·bha·ree",
                "es": "nind·ba·ri",
                "id": "nind·bha·ri",
                "fr": "nind·bha·ri",
                "it": "nind·bha·ri",
                "pt": "nind·bha·ri",
                "zh": "尼德·巴里",
                "ru": "нинд·бха·ри",
                "ja": "ニーンド·バリ",
                "hi": "नींद·भ·री",
                "fil": "nind·bha·ri",
                "th": "นีนด์·บา·รี",
                "ko": "닌드·바·리",
                "nl": "nind·bha·ri",
                "sv": "nind·bha·ri",
                "pl": "nind·bha·ri",
                "el": "νιντ·μπα·ρι",
                "de": "nind·bha·ri"
            }
        },
        "fil": {
            "text": "antok",
            "exampleSentence": "Mukhang inaantok ka, magpahinga ka.",
            "pronunciations": {
                "tr": "an·tok",
                "en": "ahn·tok",
                "es": "an·tok",
                "id": "an·tok",
                "fr": "an·tok",
                "it": "an·tok",
                "pt": "an·tok",
                "zh": "安托克",
                "ru": "ан·ток",
                "ja": "アン·トク",
                "hi": "अन्·तोक",
                "fil": "an·tok",
                "th": "อัน·ตก",
                "ko": "안·톡",
                "nl": "an·tok",
                "sv": "an·tok",
                "pl": "an·tok",
                "el": "αν·τοκ",
                "de": "an·tok"
            }
        },
        "th": {
            "text": "ง่วง",
            "romanized": "nguang",
            "exampleSentence": "คุณดูง่วง ไปพักผ่อนเถอะ",
            "romanizedExample": "Khun duu nguang, pai phak phon thoe",
            "pronunciations": {
                "tr": "ngu·ang",
                "en": "ngoo·ang",
                "es": "ngu·ang",
                "id": "ngu·ang",
                "fr": "ngu·ang",
                "it": "ngu·ang",
                "pt": "ngu·ang",
                "zh": "恩瓜",
                "ru": "нгу·анг",
                "ja": "グアン",
                "hi": "न्गु·आंग",
                "fil": "ngu·ang",
                "th": "ง่วง",
                "ko": "응우·앙",
                "nl": "ngoe·ang",
                "sv": "ngu·ang",
                "pl": "ngu·ang",
                "el": "νγκου·άνγκ",
                "de": "ngu·ang"
            }
        },
        "ko": {
            "text": "졸린",
            "romanized": "jollin",
            "exampleSentence": "졸려 보이네요, 쉬세요.",
            "romanizedExample": "Jollyeo boineyo, swiseyo.",
            "pronunciations": {
                "tr": "col·lin",
                "en": "jol·leen",
                "es": "jol·lin",
                "id": "jol·lin",
                "fr": "jol·lin",
                "it": "jol·lin",
                "pt": "jol·lin",
                "zh": "卓林",
                "ru": "чоль·лин",
                "ja": "ジョル·リン",
                "hi": "जोल्·लिन",
                "fil": "jol·lin",
                "th": "จอล·ลิน",
                "ko": "졸·린",
                "nl": "jol·lin",
                "sv": "jol·lin",
                "pl": "czol·lin",
                "el": "τζολ·λιν",
                "de": "jol·lin"
            }
        },
        "nl": {
            "text": "slaperig",
            "exampleSentence": "Je ziet er slaperig uit, ga rusten.",
            "pronunciations": {
                "tr": "sla·pe·rih",
                "en": "slah·puh·rikh",
                "es": "sla·pe·rig",
                "id": "sla·pe·rig",
                "fr": "sla·pe·rikh",
                "it": "sla·pe·rig",
                "pt": "sla·pe·rig",
                "zh": "斯拉佩里赫",
                "ru": "сла·пе·рих",
                "ja": "スラ·ペ·リッヒ",
                "hi": "स्ला·पे·रिख",
                "fil": "sla·pe·rig",
                "th": "สลา·เป·ริค",
                "ko": "슬라·페·리흐",
                "nl": "sla·pe·rig",
                "sv": "sla·pe·rig",
                "pl": "sla·pe·rih",
                "el": "σλά·πε·ριχ",
                "de": "sla·pe·rich"
            }
        },
        "sv": {
            "text": "sömnig",
            "exampleSentence": "Du ser sömnig ut, gå och vila.",
            "pronunciations": {
                "tr": "söm·nig",
                "en": "sum·nig",
                "es": "som·nig",
                "id": "som·nig",
                "fr": "som·nig",
                "it": "som·nig",
                "pt": "som·nig",
                "zh": "瑟姆尼格",
                "ru": "сём·ниг",
                "ja": "ソム·ニグ",
                "hi": "सम्·निग",
                "fil": "som·nig",
                "th": "ซอม·นิก",
                "ko": "솜·니그",
                "nl": "sum·nig",
                "sv": "söm·nig",
                "pl": "som·nig",
                "el": "σομ·νιγκ",
                "de": "söm·nig"
            }
        },
        "pl": {
            "text": "senny",
            "exampleSentence": "Wyglądasz na sennego, idź odpocząć.",
            "pronunciations": {
                "tr": "sen·ni",
                "en": "sen·ny",
                "es": "sen·ni",
                "id": "sen·ny",
                "fr": "sen·ny",
                "it": "sen·ny",
                "pt": "sen·ny",
                "zh": "森尼",
                "ru": "сен·ны",
                "ja": "セン·ニ",
                "hi": "सेन्·नी",
                "fil": "sen·ny",
                "th": "เซน·นี",
                "ko": "센·니",
                "nl": "sen·ny",
                "sv": "sen·ny",
                "pl": "sen·ny",
                "el": "σέν·νι",
                "de": "sen·ny"
            }
        },
        "el": {
            "text": "νυσταγμένος",
            "romanized": "nystagmenos",
            "exampleSentence": "Φαίνεσαι νυσταγμένος, πήγαινε να ξεκουραστείς.",
            "romanizedExample": "Fainese nystagmenos, pigaine na xekourasteis.",
            "pronunciations": {
                "tr": "nis·tag·me·nos",
                "en": "nee·stag·me·nos",
                "es": "nis·tag·me·nos",
                "id": "nis·tag·me·nos",
                "fr": "nis·tag·me·nos",
                "it": "nis·tag·me·nos",
                "pt": "nis·tag·me·nos",
                "zh": "尼斯塔格梅诺斯",
                "ru": "ни·стаг·ме·нос",
                "ja": "ニス·タグ·メ·ノス",
                "hi": "निस्·ताग्·मे·नोस",
                "fil": "nis·tag·me·nos",
                "th": "นิส·ทัก·เม·นอส",
                "ko": "니스·타그·메·노스",
                "nl": "nis·tag·me·nos",
                "sv": "nis·tag·me·nos",
                "pl": "ni·stag·me·nos",
                "el": "νυ·σταγ·μέ·νος",
                "de": "ni·stag·me·nos"
            }
        },
        "de": {
            "text": "schläfrig",
            "exampleSentence": "Du siehst schläfrig aus, geh dich ausruhen.",
            "pronunciations": {
                "tr": "şlef·rig",
                "en": "shlay·frig",
                "es": "shlef·rig",
                "id": "shlef·rig",
                "fr": "chlef·rig",
                "it": "shlef·rig",
                "pt": "shlef·rig",
                "zh": "施莱夫里希",
                "ru": "шле·фриг",
                "ja": "シュレー·フリヒ",
                "hi": "श्ले·फ्रिग",
                "fil": "shlef·rig",
                "th": "ชเล·ฟริก",
                "ko": "슐레·프리히",
                "nl": "sle·frig",
                "sv": "sle·frig",
                "pl": "szle·frig",
                "el": "σλέ·φριχ",
                "de": "schlä·frig"
            }
        }
    }
}
